{
  "provider": "example",
  "raw": {
    "match_id": "693bbe759debaa9dc4cac9e8",
    "match_date": null,
    "winner": "Punjab De Sher CC",
    "team_scores": {
      "Punjab De Sher CC": {
        "runs": 121,
        "wickets": 2,
        "overs": 9
      },
      "Lucknow Nawabs": {
        "runs": 117,
        "wickets": 5,
        "overs": 10
      }
    },
    "players": [
      {
        "name": "Travis Head",
        "team": "Punjab De Sher CC",
        "raw_stats": {
          "runs": 73,
          "wickets": 0
        }
      },
      {
        "name": "Aiden Markram",
        "team": "Punjab De Sher CC",
        "raw_stats": {
          "runs": 37,
          "wickets": 0
        }
      },
      {
        "name": "Harry Brook",
        "team": "Punjab De Sher CC",
        "raw_stats": {
          "runs": 6,
          "wickets": 0
        }
      },
      {
        "name": "Abhishek Sharma",
        "team": "Punjab De Sher CC",
        "raw_stats": {
          "runs": 0,
          "wickets": 0
        }
      },
      {
        "name": "Kyle Jamieson",
        "team": "Punjab De Sher CC",
        "raw_stats": {
          "runs": 0,
          "wickets": 2
        }
      },
      {
        "name": "Mohammed Shami",
        "team": "Punjab De Sher CC",
        "raw_stats": {
          "runs": 0,
          "wickets": 1
        }
      },
      {
        "name": "Kuldeep Yadav",
        "team": "Punjab De Sher CC",
        "raw_stats": {
          "runs": 0,
          "wickets": 1
        }
      },
      {
        "name": "Matt Henry",
        "team": "Punjab De Sher CC",
        "raw_stats": {
          "runs": 0,
          "wickets": 1
        }
      },
      {
        "name": "Ben Stokes",
        "team": "Punjab De Sher CC",
        "raw_stats": {
          "runs": 0,
          "wickets": 0
        }
      },
      {
        "name": "Zak Crawley",
        "team": "Lucknow Nawabs",
        "raw_stats": {
          "runs": 21,
          "wickets": 0
        }
      },
      {
        "name": "Quinton de Kock",
        "team": "Lucknow Nawabs",
        "raw_stats": {
          "runs": 16,
          "wickets": 0
        }
      },
      {
        "name": "Virat Kohli",
        "team": "Lucknow Nawabs",
        "raw_stats": {
          "runs": 15,
          "wickets": 0
        }
      },
      {
        "name": "Sanju Samson",
        "team": "Lucknow Nawabs",
        "raw_stats": {
          "runs": 6,
          "wickets": 0
        }
      },
      {
        "name": "Suryakumar Yadav",
        "team": "Lucknow Nawabs",
        "raw_stats": {
          "runs": 29,
          "wickets": 0
        }
      },
      {
        "name": "Rohit Sharma",
        "team": "Lucknow Nawabs",
        "raw_stats": {
          "runs": 30,
          "wickets": 0
        }
      },
      {
        "name": "Ravindra Jadeja",
        "team": "Lucknow Nawabs",
        "raw_stats": {
          "runs": 0,
          "wickets": 0
        }
      },
      {
        "name": "Harshit Rana",
        "team": "Lucknow Nawabs",
        "raw_stats": {
          "runs": 0,
          "wickets": 1
        }
      },
      {
        "name": "Trent Boult",
        "team": "Lucknow Nawabs",
        "raw_stats": {
          "runs": 0,
          "wickets": 1
        }
      },
      {
        "name": "Sikandar Raza",
        "team": "Lucknow Nawabs",
        "raw_stats": {
          "runs": 0,
          "wickets": 0
        }
      },
      {
        "name": "Jasprit Bumrah",
        "team": "Lucknow Nawabs",
        "raw_stats": {
          "runs": 0,
          "wickets": 0
        }
      }
    ]
  }
}